vocab_study_cli/__init__.py
vocab_study_cli/audio.py
vocab_study_cli/image.py
vocab_study_cli/main.py
vocab_study_cli-0.2.0.dist-info/METADATA
vocab_study_cli-0.2.0.dist-info/WHEEL
vocab_study_cli-0.2.0.dist-info/entry_points.txt
vocab_study_cli-0.2.0.dist-info/RECORD
